NiuKeyunYinggangMianshiZhentiBaodian20212022/README.md
NiuKeyunYinggangMianshiZhentiBaodian20212022/__init__.py
NiuKeyunYinggangMianshiZhentiBaodian20212022/__main__.py
NiuKeyunYinggangMianshiZhentiBaodian20212022/file.epub
NiuKeyunYinggangMianshiZhentiBaodian20212022/index.html
NiuKeyunYinggangMianshiZhentiBaodian20212022/css/__init__.py
NiuKeyunYinggangMianshiZhentiBaodian20212022/css/annotations.css
NiuKeyunYinggangMianshiZhentiBaodian20212022/css/main.css
NiuKeyunYinggangMianshiZhentiBaodian20212022/css/normalize.css
NiuKeyunYinggangMianshiZhentiBaodian20212022/css/popup.css
NiuKeyunYinggangMianshiZhentiBaodian20212022/font/__init__.py
NiuKeyunYinggangMianshiZhentiBaodian20212022/font/fontello.eot
NiuKeyunYinggangMianshiZhentiBaodian20212022/font/fontello.svg
NiuKeyunYinggangMianshiZhentiBaodian20212022/font/fontello.ttf
NiuKeyunYinggangMianshiZhentiBaodian20212022/font/fontello.woff
NiuKeyunYinggangMianshiZhentiBaodian20212022/img/__init__.py
NiuKeyunYinggangMianshiZhentiBaodian20212022/img/annotator-glyph-sprite.png
NiuKeyunYinggangMianshiZhentiBaodian20212022/img/annotator-icon-sprite.png
NiuKeyunYinggangMianshiZhentiBaodian20212022/img/apple-touch-icon.png
NiuKeyunYinggangMianshiZhentiBaodian20212022/img/cancelfullscreen.png
NiuKeyunYinggangMianshiZhentiBaodian20212022/img/close.png
NiuKeyunYinggangMianshiZhentiBaodian20212022/img/fullscreen.png
NiuKeyunYinggangMianshiZhentiBaodian20212022/img/loader.gif
NiuKeyunYinggangMianshiZhentiBaodian20212022/img/menu-icon.png
NiuKeyunYinggangMianshiZhentiBaodian20212022/img/save.png
NiuKeyunYinggangMianshiZhentiBaodian20212022/img/saved.png
NiuKeyunYinggangMianshiZhentiBaodian20212022/img/settings-s.png
NiuKeyunYinggangMianshiZhentiBaodian20212022/img/settings.png
NiuKeyunYinggangMianshiZhentiBaodian20212022/img/star.png
NiuKeyunYinggangMianshiZhentiBaodian20212022/js/__init__.py
NiuKeyunYinggangMianshiZhentiBaodian20212022/js/epub.js
NiuKeyunYinggangMianshiZhentiBaodian20212022/js/epub.min.js
niu_keyun_yinggang_mianshi_zhenti_baodian_2021_2022-2024.3.6.0.dist-info/METADATA
niu_keyun_yinggang_mianshi_zhenti_baodian_2021_2022-2024.3.6.0.dist-info/WHEEL
niu_keyun_yinggang_mianshi_zhenti_baodian_2021_2022-2024.3.6.0.dist-info/entry_points.txt
niu_keyun_yinggang_mianshi_zhenti_baodian_2021_2022-2024.3.6.0.dist-info/top_level.txt
niu_keyun_yinggang_mianshi_zhenti_baodian_2021_2022-2024.3.6.0.dist-info/RECORD
